{
  "reflexia_state": {
    "active": true,
    "last_reflection": "2025-06-29T00:21:47.412318",
    "status": "degraded",
    "metrics": {
      "cpu": 16.8,
      "ram": 70.0,
      "latency": 1112.04,
      "containers": 0,
      "modules_active": 2,
      "errors": 6
    },
    "confidence_level": 0.85
  },
  "zeroia_state": {
    "last_execution": "2025-06-28T22:21:26.105019",
    "recent_errors": [],
    "status": "active",
    "decision_metrics": {
      "confidence": 0.897854824059641,
      "accuracy": 0.8604134053114428
    },
    "active": true,
    "context": {
      "status": {
        "severity": "normal"
      }
    }
  },
  "assistant_state": {
    "active": true,
    "session_count": 0,
    "last_interaction": "2025-06-29T00:21:47.412587"
  },
  "coherence_analysis": {
    "coherence_score": 1.0,
    "issues": [],
    "last_analysis": "2025-06-29T00:21:47.412591",
    "modules_aligned": true
  },
  "behavioral_patterns": [],
  "recommendations": [
    "Syst\u00e8me d'intelligence crois\u00e9e fonctionnel"
  ]
}
