{
  "reflexia_state": {
    "active": true,
    "last_reflection": "2025-06-29T13:23:38.527403",
    "status": "ok",
    "metrics": {
      "cpu": 45.2,
      "ram": 62.8,
      "latency": 29.2,
      "containers": 0,
      "modules_active": 2,
      "errors": 6
    },
    "confidence_level": 0.85
  },
  "zeroia_state": {
    "last_execution": "2025-06-29T13:23:08.273463",
    "recent_errors": [],
    "status": "active",
    "decision_metrics": {
      "confidence": 0.8695179689369786,
      "accuracy": 0.8693683860562564
    },
    "active": true,
    "context": {
      "last_update": "2025-06-29T13:23:08.273472",
      "system_status": "operational",
      "active_modules": [
        "reflexia",
        "zeroia",
        "assistantia"
      ]
    }
  },
  "assistant_state": {
    "active": true,
    "session_count": 0,
    "last_interaction": "2025-06-29T13:23:38.527410"
  },
  "coherence_analysis": {
    "coherence_score": 1.0,
    "issues": [],
    "last_analysis": "2025-06-29T13:23:38.527412",
    "modules_aligned": true
  },
  "behavioral_patterns": [],
  "recommendations": [
    "Syst\u00e8me d'intelligence crois\u00e9e fonctionnel"
  ]
}