{".class":"MypyFile","_fullname":"modules.monitoring.core","future_import_flags":[],"is_partial_stub_package":false,"is_stub":false,"names":{".class":"SymbolTable","Any":{".class":"SymbolTableNode","cross_ref":"typing.Any","kind":"Gdef"},"Optional":{".class":"SymbolTableNode","cross_ref":"typing.Optional","kind":"Gdef"},"Path":{".class":"SymbolTableNode","cross_ref":"pathlib.Path","kind":"Gdef"},"UmonitoringConfig":{".class":"SymbolTableNode","kind":"Gdef","node":{".class":"TypeInfo","_promote":[],"abstract_attributes":[],"alt_promote":null,"bases":["builtins.object"],"dataclass_transform_spec":null,"declared_metaclass":null,"defn":{".class":"ClassDef","fullname":"modules.monitoring.core.UmonitoringConfig","name":"UmonitoringConfig","type_vars":[]},"deletable_attributes":[],"deprecated":null,"flags":[],"fullname":"modules.monitoring.core.UmonitoringConfig","has_param_spec_type":false,"metaclass_type":null,"metadata":{"dataclass":{"attributes":[{"alias":null,"column":4,"has_default":true,"is_in_init":true,"is_init_var":false,"is_neither_frozen_nor_nonfrozen":false,"kw_only":false,"line":25,"name":"enabled","type":"builtins.bool"},{"alias":null,"column":4,"has_default":true,"is_in_init":true,"is_init_var":false,"is_neither_frozen_nor_nonfrozen":false,"kw_only":false,"line":26,"name":"debug_mode","type":"builtins.bool"},{"alias":null,"column":4,"has_default":true,"is_in_init":true,"is_init_var":false,"is_neither_frozen_nor_nonfrozen":false,"kw_only":false,"line":27,"name":"max_retries","type":"builtins.int"},{"alias":null,"column":4,"has_default":true,"is_in_init":true,"is_init_var":false,"is_neither_frozen_nor_nonfrozen":false,"kw_only":false,"line":28,"name":"timeout","type":"builtins.float"}],"frozen":false},"dataclass_tag":{}},"module_name":"modules.monitoring.core","mro":["modules.monitoring.core.UmonitoringConfig","builtins.object"],"names":{".class":"SymbolTable","__dataclass_fields__":{".class":"SymbolTableNode","kind":"Mdef","node":{".class":"Var","flags":["is_classvar","is_ready"],"fullname":"modules.monitoring.core.UmonitoringConfig.__dataclass_fields__","name":"__dataclass_fields__","type":{".class":"Instance","args":["builtins.str",{".class":"Instance","args":[{".class":"AnyType","missing_import_name":null,"source_any":null,"type_of_any":2}],"extra_attrs":null,"type_ref":"dataclasses.Field"}],"extra_attrs":null,"type_ref":"builtins.dict"}},"plugin_generated":true},"__init__":{".class":"SymbolTableNode","kind":"Mdef","node":{".class":"FuncDef","abstract_status":0,"arg_kinds":[0,1,1,1,1],"arg_names":["self","enabled","debug_mode","max_retries","timeout"],"dataclass_transform_spec":null,"deprecated":null,"flags":[],"fullname":"modules.monitoring.core.UmonitoringConfig.__init__","name":"__init__","type":{".class":"CallableType","arg_kinds":[0,1,1,1,1],"arg_names":["self","enabled","debug_mode","max_retries","timeout"],"arg_types":["modules.monitoring.core.UmonitoringConfig","builtins.bool","builtins.bool","builtins.int","builtins.float"],"bound_args":[],"def_extras":{},"fallback":"builtins.function","from_concatenate":false,"implicit":false,"imprecise_arg_kinds":false,"is_ellipsis_args":false,"name":"__init__ of UmonitoringConfig","ret_type":{".class":"NoneType"},"type_guard":null,"type_is":null,"unpack_kwargs":false,"variables":[]}},"plugin_generated":true},"__match_args__":{".class":"SymbolTableNode","kind":"Mdef","node":{".class":"Var","flags":["is_ready","allow_incompatible_override"],"fullname":"modules.monitoring.core.UmonitoringConfig.__match_args__","name":"__match_args__","type":{".class":"TupleType","implicit":false,"items":[{".class":"LiteralType","fallback":"builtins.str","value":"enabled"},{".class":"LiteralType","fallback":"builtins.str","value":"debug_mode"},{".class":"LiteralType","fallback":"builtins.str","value":"max_retries"},{".class":"LiteralType","fallback":"builtins.str","value":"timeout"}],"partial_fallback":{".class":"Instance","args":[{".class":"AnyType","missing_import_name":null,"source_any":null,"type_of_any":6}],"extra_attrs":null,"type_ref":"builtins.tuple"}}},"plugin_generated":true},"__mypy-replace":{".class":"SymbolTableNode","kind":"Mdef","node":{".class":"Decorator","func":{".class":"FuncDef","abstract_status":0,"arg_kinds":[5,5,5,5],"arg_names":["enabled","debug_mode","max_retries","timeout"],"dataclass_transform_spec":null,"deprecated":null,"flags":["is_static","is_decorated"],"fullname":"modules.monitoring.core.UmonitoringConfig.__mypy-replace","name":"__mypy-replace","type":{".class":"CallableType","arg_kinds":[5,5,5,5],"arg_names":["enabled","debug_mode","max_retries","timeout"],"arg_types":["builtins.bool","builtins.bool","builtins.int","builtins.float"],"bound_args":[],"def_extras":{},"fallback":"builtins.function","from_concatenate":false,"implicit":false,"imprecise_arg_kinds":false,"is_ellipsis_args":false,"name":"__mypy-replace of UmonitoringConfig","ret_type":{".class":"NoneType"},"type_guard":null,"type_is":null,"unpack_kwargs":false,"variables":[]}},"is_overload":false,"var":{".class":"Var","flags":["is_staticmethod","is_ready"],"fullname":"modules.monitoring.core.UmonitoringConfig.__mypy-replace","name":"__mypy-replace","type":{".class":"CallableType","arg_kinds":[5,5,5,5],"arg_names":["enabled","debug_mode","max_retries","timeout"],"arg_types":["builtins.bool","builtins.bool","builtins.int","builtins.float"],"bound_args":[],"def_extras":{},"fallback":"builtins.function","from_concatenate":false,"implicit":false,"imprecise_arg_kinds":false,"is_ellipsis_args":false,"name":"__mypy-replace of UmonitoringConfig","ret_type":{".class":"NoneType"},"type_guard":null,"type_is":null,"unpack_kwargs":false,"variables":[]}}},"plugin_generated":true},"debug_mode":{".class":"SymbolTableNode","kind":"Mdef","node":{".class":"Var","flags":["is_initialized_in_class","is_ready","has_explicit_value"],"fullname":"modules.monitoring.core.UmonitoringConfig.debug_mode","name":"debug_mode","type":"builtins.bool"}},"enabled":{".class":"SymbolTableNode","kind":"Mdef","node":{".class":"Var","flags":["is_initialized_in_class","is_ready","has_explicit_value"],"fullname":"modules.monitoring.core.UmonitoringConfig.enabled","name":"enabled","type":"builtins.bool"}},"max_retries":{".class":"SymbolTableNode","kind":"Mdef","node":{".class":"Var","flags":["is_initialized_in_class","is_ready","has_explicit_value"],"fullname":"modules.monitoring.core.UmonitoringConfig.max_retries","name":"max_retries","type":"builtins.int"}},"timeout":{".class":"SymbolTableNode","kind":"Mdef","node":{".class":"Var","flags":["is_initialized_in_class","is_ready","has_explicit_value"],"fullname":"modules.monitoring.core.UmonitoringConfig.timeout","name":"timeout","type":"builtins.float"}}},"self_type":{".class":"TypeVarType","default":{".class":"AnyType","missing_import_name":null,"source_any":null,"type_of_any":4},"fullname":"modules.monitoring.core.UmonitoringConfig.Self","id":0,"name":"Self","namespace":"","upper_bound":"modules.monitoring.core.UmonitoringConfig","values":[],"variance":0},"slots":null,"tuple_type":null,"type_vars":[],"typeddict_type":null}},"UmonitoringCore":{".class":"SymbolTableNode","kind":"Gdef","node":{".class":"TypeInfo","_promote":[],"abstract_attributes":[],"alt_promote":null,"bases":["builtins.object"],"dataclass_transform_spec":null,"declared_metaclass":null,"defn":{".class":"ClassDef","fullname":"modules.monitoring.core.UmonitoringCore","name":"UmonitoringCore","type_vars":[]},"deletable_attributes":[],"deprecated":null,"flags":[],"fullname":"modules.monitoring.core.UmonitoringCore","has_param_spec_type":false,"metaclass_type":null,"metadata":{},"module_name":"modules.monitoring.core","mro":["modules.monitoring.core.UmonitoringCore","builtins.object"],"names":{".class":"SymbolTable","__init__":{".class":"SymbolTableNode","kind":"Mdef","node":{".class":"FuncDef","abstract_status":0,"arg_kinds":[0,0],"arg_names":["self","config"],"dataclass_transform_spec":null,"deprecated":null,"flags":[],"fullname":"modules.monitoring.core.UmonitoringCore.__init__","name":"__init__","type":{".class":"CallableType","arg_kinds":[0,0],"arg_names":["self","config"],"arg_types":["modules.monitoring.core.UmonitoringCore","modules.monitoring.core.UmonitoringConfig"],"bound_args":[],"def_extras":{"first_arg":"self"},"fallback":"builtins.function","from_concatenate":false,"implicit":false,"imprecise_arg_kinds":false,"is_ellipsis_args":false,"name":"__init__ of UmonitoringCore","ret_type":{".class":"NoneType"},"type_guard":null,"type_is":null,"unpack_kwargs":false,"variables":[]}}},"_initialize":{".class":"SymbolTableNode","kind":"Mdef","node":{".class":"FuncDef","abstract_status":0,"arg_kinds":[0],"arg_names":["self"],"dataclass_transform_spec":null,"deprecated":null,"flags":[],"fullname":"modules.monitoring.core.UmonitoringCore._initialize","name":"_initialize","type":{".class":"CallableType","arg_kinds":[0],"arg_names":["self"],"arg_types":["modules.monitoring.core.UmonitoringCore"],"bound_args":[],"def_extras":{"first_arg":"self"},"fallback":"builtins.function","from_concatenate":false,"implicit":false,"imprecise_arg_kinds":false,"is_ellipsis_args":false,"name":"_initialize of UmonitoringCore","ret_type":{".class":"NoneType"},"type_guard":null,"type_is":null,"unpack_kwargs":false,"variables":[]}}},"config":{".class":"SymbolTableNode","implicit":true,"kind":"Mdef","node":{".class":"Var","flags":["is_inferred"],"fullname":"modules.monitoring.core.UmonitoringCore.config","name":"config","type":"modules.monitoring.core.UmonitoringConfig"}},"health_check":{".class":"SymbolTableNode","kind":"Mdef","node":{".class":"FuncDef","abstract_status":0,"arg_kinds":[0],"arg_names":["self"],"dataclass_transform_spec":null,"deprecated":null,"flags":[],"fullname":"modules.monitoring.core.UmonitoringCore.health_check","name":"health_check","type":{".class":"CallableType","arg_kinds":[0],"arg_names":["self"],"arg_types":["modules.monitoring.core.UmonitoringCore"],"bound_args":[],"def_extras":{"first_arg":"self"},"fallback":"builtins.function","from_concatenate":false,"implicit":false,"imprecise_arg_kinds":false,"is_ellipsis_args":false,"name":"health_check of UmonitoringCore","ret_type":{".class":"Instance","args":["builtins.str",{".class":"AnyType","missing_import_name":null,"source_any":null,"type_of_any":2}],"extra_attrs":null,"type_ref":"builtins.dict"},"type_guard":null,"type_is":null,"unpack_kwargs":false,"variables":[]}}},"logger":{".class":"SymbolTableNode","implicit":true,"kind":"Mdef","node":{".class":"Var","flags":["is_inferred"],"fullname":"modules.monitoring.core.UmonitoringCore.logger","name":"logger","type":"logging.Logger"}},"process":{".class":"SymbolTableNode","kind":"Mdef","node":{".class":"FuncDef","abstract_status":0,"arg_kinds":[0,0],"arg_names":["self","data"],"dataclass_transform_spec":null,"deprecated":null,"flags":["is_coroutine"],"fullname":"modules.monitoring.core.UmonitoringCore.process","name":"process","type":{".class":"CallableType","arg_kinds":[0,0],"arg_names":["self","data"],"arg_types":["modules.monitoring.core.UmonitoringCore",{".class":"Instance","args":["builtins.str",{".class":"AnyType","missing_import_name":null,"source_any":null,"type_of_any":2}],"extra_attrs":null,"type_ref":"builtins.dict"}],"bound_args":[],"def_extras":{"first_arg":"self"},"fallback":"builtins.function","from_concatenate":false,"implicit":false,"imprecise_arg_kinds":false,"is_ellipsis_args":false,"name":"process of UmonitoringCore","ret_type":{".class":"Instance","args":[{".class":"AnyType","missing_import_name":null,"source_any":null,"type_of_any":6},{".class":"AnyType","missing_import_name":null,"source_any":null,"type_of_any":6},{".class":"Instance","args":["builtins.str",{".class":"AnyType","missing_import_name":null,"source_any":null,"type_of_any":2}],"extra_attrs":null,"type_ref":"builtins.dict"}],"extra_attrs":null,"type_ref":"typing.Coroutine"},"type_guard":null,"type_is":null,"unpack_kwargs":false,"variables":[]}}}},"self_type":{".class":"TypeVarType","default":{".class":"AnyType","missing_import_name":null,"source_any":null,"type_of_any":4},"fullname":"modules.monitoring.core.UmonitoringCore.Self","id":0,"name":"Self","namespace":"","upper_bound":"modules.monitoring.core.UmonitoringCore","values":[],"variance":0},"slots":null,"tuple_type":null,"type_vars":[],"typeddict_type":null}},"__annotations__":{".class":"SymbolTableNode","kind":"Gdef","node":{".class":"Var","flags":["is_ready"],"fullname":"modules.monitoring.core.__annotations__","name":"__annotations__","type":{".class":"Instance","args":["builtins.str",{".class":"AnyType","missing_import_name":null,"source_any":null,"type_of_any":6}],"extra_attrs":null,"type_ref":"builtins.dict"}}},"__doc__":{".class":"SymbolTableNode","kind":"Gdef","node":{".class":"Var","flags":["is_ready"],"fullname":"modules.monitoring.core.__doc__","name":"__doc__","type":"builtins.str"}},"__file__":{".class":"SymbolTableNode","kind":"Gdef","node":{".class":"Var","flags":["is_ready"],"fullname":"modules.monitoring.core.__file__","name":"__file__","type":"builtins.str"}},"__name__":{".class":"SymbolTableNode","kind":"Gdef","node":{".class":"Var","flags":["is_ready"],"fullname":"modules.monitoring.core.__name__","name":"__name__","type":"builtins.str"}},"__package__":{".class":"SymbolTableNode","kind":"Gdef","node":{".class":"Var","flags":["is_ready"],"fullname":"modules.monitoring.core.__package__","name":"__package__","type":"builtins.str"}},"__spec__":{".class":"SymbolTableNode","kind":"Gdef","node":{".class":"Var","flags":["is_ready"],"fullname":"modules.monitoring.core.__spec__","name":"__spec__","type":"_frozen_importlib.ModuleSpec"}},"asyncio":{".class":"SymbolTableNode","cross_ref":"asyncio","kind":"Gdef"},"dataclass":{".class":"SymbolTableNode","cross_ref":"dataclasses.dataclass","kind":"Gdef"},"default_config":{".class":"SymbolTableNode","kind":"Gdef","node":{".class":"Var","flags":["is_inferred","has_explicit_value"],"fullname":"modules.monitoring.core.default_config","name":"default_config","type":"modules.monitoring.core.UmonitoringConfig"}},"default_core":{".class":"SymbolTableNode","kind":"Gdef","node":{".class":"Var","flags":["is_inferred","has_explicit_value"],"fullname":"modules.monitoring.core.default_core","name":"default_core","type":"modules.monitoring.core.UmonitoringCore"}},"logger":{".class":"SymbolTableNode","kind":"Gdef","node":{".class":"Var","flags":["is_inferred","has_explicit_value"],"fullname":"modules.monitoring.core.logger","name":"logger","type":"logging.Logger"}},"logging":{".class":"SymbolTableNode","cross_ref":"logging","kind":"Gdef"},"main":{".class":"SymbolTableNode","kind":"Gdef","node":{".class":"FuncDef","abstract_status":0,"arg_kinds":[],"arg_names":[],"dataclass_transform_spec":null,"deprecated":null,"flags":["is_coroutine"],"fullname":"modules.monitoring.core.main","name":"main","type":null}}},"path":"/Volumes/T7/devstation/cursor/arkalia-luna-pro/modules/monitoring/core.py"}